sgllm/__init__.py
sgllm/__main__.py
sgllm/_base_client.py
sgllm/_client.py
sgllm/_compat.py
sgllm/_constants.py
sgllm/_exceptions.py
sgllm/_extras/__init__.py
sgllm/_extras/_common.py
sgllm/_extras/numpy_proxy.py
sgllm/_extras/pandas_proxy.py
sgllm/_files.py
sgllm/_legacy_response.py
sgllm/_models.py
sgllm/_module_client.py
sgllm/_qs.py
sgllm/_resource.py
sgllm/_response.py
sgllm/_streaming.py
sgllm/_types.py
sgllm/_utils/__init__.py
sgllm/_utils/_logs.py
sgllm/_utils/_proxy.py
sgllm/_utils/_streams.py
sgllm/_utils/_sync.py
sgllm/_utils/_transform.py
sgllm/_utils/_typing.py
sgllm/_utils/_utils.py
sgllm/_version.py
sgllm/cli/__init__.py
sgllm/cli/_api/__init__.py
sgllm/cli/_api/_main.py
sgllm/cli/_api/audio.py
sgllm/cli/_api/chat/__init__.py
sgllm/cli/_api/chat/completions.py
sgllm/cli/_api/completions.py
sgllm/cli/_api/files.py
sgllm/cli/_api/image.py
sgllm/cli/_api/models.py
sgllm/cli/_cli.py
sgllm/cli/_errors.py
sgllm/cli/_models.py
sgllm/cli/_progress.py
sgllm/cli/_tools/__init__.py
sgllm/cli/_tools/_main.py
sgllm/cli/_tools/fine_tunes.py
sgllm/cli/_tools/migrate.py
sgllm/cli/_utils.py
sgllm/lib/.keep
sgllm/lib/_old_api.py
sgllm/lib/_validators.py
sgllm/lib/azure.py
sgllm/lib/streaming/__init__.py
sgllm/lib/streaming/_assistants.py
sgllm/pagination.py
sgllm/py.typed
sgllm/resources/__init__.py
sgllm/resources/audio/__init__.py
sgllm/resources/audio/audio.py
sgllm/resources/audio/speech.py
sgllm/resources/audio/transcriptions.py
sgllm/resources/audio/translations.py
sgllm/resources/batches.py
sgllm/resources/beta/__init__.py
sgllm/resources/beta/assistants.py
sgllm/resources/beta/beta.py
sgllm/resources/beta/threads/__init__.py
sgllm/resources/beta/threads/messages.py
sgllm/resources/beta/threads/runs/__init__.py
sgllm/resources/beta/threads/runs/runs.py
sgllm/resources/beta/threads/runs/steps.py
sgllm/resources/beta/threads/threads.py
sgllm/resources/beta/vector_stores/__init__.py
sgllm/resources/beta/vector_stores/file_batches.py
sgllm_python-0.1.2.dist-info/LICENSE
sgllm_python-0.1.2.dist-info/METADATA
sgllm_python-0.1.2.dist-info/WHEEL
sgllm_python-0.1.2.dist-info/RECORD
