Metadata-Version: 2.1
Name: sgllm-python
Version: 0.1.2
Summary: The Official Python Library For The SGLLM API.
License: MIT
Author: JueYing
Author-email: jueying@aiunicorn.com
Requires-Python: >=3.7.1,<3.13
Classifier: License :: OSI Approved :: MIT License
Classifier: Programming Language :: Python :: 3
Classifier: Programming Language :: Python :: 3.8
Classifier: Programming Language :: Python :: 3.9
Classifier: Programming Language :: Python :: 3.10
Classifier: Programming Language :: Python :: 3.11
Classifier: Programming Language :: Python :: 3.12
Requires-Dist: anyio (>=3.5.0,<5)
Requires-Dist: cached-property (>=1.5.2,<2.0.0) ; python_version < "3.8"
Requires-Dist: distro (>=1.7.0,<2)
Requires-Dist: httpx (>=0.23.0,<1)
Requires-Dist: numpy (>=1)
Requires-Dist: pandas (>=1.2.3)
Requires-Dist: pandas-stubs (>=1.1.0.11)
Requires-Dist: pydantic (>=1.9.0,<3)
Requires-Dist: sniffio
Requires-Dist: tqdm
Requires-Dist: typing-extensions (>=4.7,<5)
